LICENSE
deathstar/__init__.py
deathstar/crystals/lateral_movement/invoke_psremoting.py
deathstar/crystals/lateral_movement/invoke_wmi.py
deathstar/crystals/postex/get_lapspasswords.py
deathstar/crystals/postex/invoke_internal_monologue.py
deathstar/crystals/postex/mimikatz.py
deathstar/crystals/postex/powerdump.py
deathstar/crystals/postex/psinject.py
deathstar/crystals/postex/spawnas.py
deathstar/crystals/postex/tasklist.py
deathstar/crystals/privesc/domain/gpp.py
deathstar/crystals/privesc/local/ask.py
deathstar/crystals/privesc/local/bypassuac_eventvwr.py
deathstar/crystals/recon/find_localadmin_access.py
deathstar/crystals/recon/get_domain_controller.py
deathstar/crystals/recon/get_domain_sid.py
deathstar/crystals/recon/get_gpo_computer.py
deathstar/crystals/recon/get_group_member.py
deathstar/crystals/recon/get_localgroup.py
deathstar/crystals/recon/get_loggedon.py
deathstar/crystals/recon/get_rdp_session.py
deathstar/crystals/recon/get_session.py
deathstar/crystals/recon/user_hunter.py
deathstar/deathstar.py
deathstar/empire.py
deathstar/kybercrystals.py
deathstar/planetaryrecon.py
deathstar/utils.py
deathstar_empire-0.2.0.dist-info/entry_points.txt
deathstar_empire-0.2.0.dist-info/LICENSE
deathstar_empire-0.2.0.dist-info/WHEEL
deathstar_empire-0.2.0.dist-info/METADATA
deathstar_empire-0.2.0.dist-info/RECORD
