Metadata-Version: 2.1
Name: deathstar-empire
Version: 0.2.0
Summary: Uses Empire's RESTful API to automate gaining Domain and/or Enterprise Admin rights in Active Directory environments using some of the most common offensive TTPs
Home-page: https://github.com/byt3bl33d3r/DeathStar
License: GPL-3.0-only
Author: Marcello Salvati
Author-email: byt3bl33d3r@pm.com
Requires-Python: >=3.8,<4.0
Classifier: License :: OSI Approved :: GNU General Public License v3 (GPLv3)
Classifier: Programming Language :: Python :: 3
Classifier: Programming Language :: Python :: 3.8
Classifier: Programming Language :: Python :: 3.9
Classifier: Topic :: Security
Requires-Dist: httpx (>=0.16.0,<0.17.0)
Requires-Dist: rich (>=9.4.0,<10.0.0)
Project-URL: Repository, https://github.com/byt3bl33d3r/DeathStar
